papys/__init__.py
papys/authorization_hooks.py
papys/config.py
papys/core.py
papys/hooks.py
papys/http_methods.py
papys/request_response.py
papys/route.py
papys/security.py
papys/security_hooks.py
papys/server.py
papys/utils.py
papys/actions/__init__.py
papys/actions/authentication.py
papys/actions/core.py
papys/actions/decorators.py
papys/actions/error_handlers.py
papys/actions/flows.py
papys/actions/keycloak_admin.py
papys/actions/mocks.py
papys/actions/schema_validators.py
papys/actions/statics.py
papys-0.8.12.dist-info/LICENSE
papys-0.8.12.dist-info/METADATA
papys-0.8.12.dist-info/WHEEL
papys-0.8.12.dist-info/top_level.txt
papys-0.8.12.dist-info/RECORD
