Metadata-Version: 2.2
Name: papys
Version: 0.8.12
Summary: Python Rest-API as a DAG
Home-page: https://papys.asderix.com/
Author: Ronny Fuchs
Author-email: info@asderix.com
License: Apache 2.0
Classifier: Programming Language :: Python :: 3
Classifier: License :: OSI Approved :: Apache Software License
Classifier: Operating System :: OS Independent
Requires-Python: >=3.8
License-File: LICENSE
Dynamic: author
Dynamic: author-email
Dynamic: classifier
Dynamic: description
Dynamic: description-content-type
Dynamic: home-page
Dynamic: license
Dynamic: requires-python
Dynamic: summary
